Workbook
Name AttributeType: #REF!
Name AttributeType2: #REF!
Name BooleanValues: #REF!
Name brand: [1]lookup!$A$2:$A$25
Name CBD_SHOE_HEIGHT: [2]drop_down!$B$2:$B$5
Name ColorControlMode: #REF!
Name ComponentComposition: #REF!
Name CompositesConstruction: #REF!
Name coo: [1]lookup!$D$2:$D$25
Name CorrugatedMaterial: #REF!
Name CurrencyCode: #REF!
Name DisplayMode: #REF!
Name ElasticStructure: #REF!
Name EndType: #REF!
Name FoldType: #REF!
Name group: [1]lookup!$B$2:$B$25
Name HookEyeBarApp: #REF!
Name HookLoopApp: #REF!
Name HookLoopForm: #REF!
Name InternalExternal: #REF!
Name kl: #REF!
Name KnitType: #REF!
Name LabelApp: #REF!
Name LabelLanguage: #REF!
Name LeatherSatra: #REF!
Name LeatherSubtype: #REF!
Name LeatherThickness: #REF!
Name LeatherType: #REF!
Name Level: #REF!
Name lo: [1]lookup!$C$2:$C$25
Name MaterialComposition: #REF!
Name MaterialDevelopmentStatus: #REF!
Name MaterialPricingMode: #REF!
Name MaterialSupplierStatus: #REF!
Name MetalCategory: #REF!
Name MetalForm: #REF!
Name MetalShape: #REF!
Name PackagingCoatingFinishing: #REF!
Name PackagingMaterialQuality: #REF!
Name PackagingType: #REF!
Name PaymentTerms: #REF!
Name ProductSampleType: #REF!
Name RawMaterial: #REF!
Name SampleProductType: #REF!
Name SampleStatus: #REF!
Name SampleSubType: #REF!
Name SampleType: #REF!
Name Scope: #REF!
Name Shipping: #REF!
Name SizeWeight: #REF!
Name SnapCover: #REF!
Name source: [3]TechPack!$M$2:$M$11
Name SpecialClaims: #REF!
Name StampFinishPattern: #REF!
Name Standard: #REF!
Name Strength: #REF!
Name Structure: #REF!
Name SubA: [4]Materials!$M$30
Name SubB: [4]Materials!$M$36
Name SubC: [4]Materials!$M$40

Sheet Footwear-Detailed-Breakdown
M1: 6
C2: Footwear Cost Break Down
C5: PRODUCT SUMMARY
C6: SEASON: | D6: {*du|var:plmSeasonName|locked} | F6: PLM PRODUCT #: | G6: {*du|var:plmProductNumber|locked} | I6: COLORWAY NAME: | J6: {*d|var:costSheetSelectedColorwayNames|locked} | N6: USER EMAIL: | O6: {*ud|var:exportedUserMail}
C7: COST SHEET MILESTONE: | F7: PRODUCT DESCRIPTION: | G7: {*d|var:scProductDescription|locked|ft:com.lcs.wc.product.LCSProduct} | I7: COLORWAY #: | J7: {*du|var:costSheetSelectedColorwayIds|locked} | N7: REP COLORWAY FORECAST: | O7: {*d|var:scInitialEstimatedUnits|locked|ft:com.lcs.wc.season.LCSSKUSeasonLink}
C8: COST SHEET NAME: | D8: {*du|var:name} | F8: GENDER: | G8: {*d|var:scGender|locked|ft:com.lcs.wc.product.LCSProduct} | I8: REPRESENTATIVE COLORWAY: | J8: {*d|var:representativeColorwayName|locked} | N8: TARGET VENDOR QUOTE: | O8: {*d|var:scTargetVendorQuote|locked|ft:com.lcs.wc.sourcing.LCSCostSheet}
C9: COST SHEET NUMBER: | D9: {*du|var:scCostSheetNumber|locked} | F9: AGE GROUP: | G9: {*d|var:scAge|locked|ft:com.lcs.wc.product.LCSProduct} | I9: SIZE RANGE: | J9: {*d|var:scSizeRange|locked|ft:com.lcs.wc.product.LCSProduct}
C10: SOURCING CONFIG: | D10: {*d|var:sourcingConfigName|locked} | F10: DEVELOPMENT TYPE: | G10: {*d|var:scdevelopmentype|locked|ft:com.lcs.wc.season.LCSSeasonProductLink} | I10: COSTING SIZE: | J10: {*ud|var:scCostingSize|ft:com.lcs.wc.sourcing.LCSCostSheet}
C11: COUNTRY OF ORIGIN | D11: {*d|var:countryOfOrigin|locked} | F11: OUTSOLE: | G11: {*d|var:scOutsole|locked|ft:com.lcs.wc.product.LCSProduct} | I11: SAMPLE SIZE:
C12: SPECIFICATION: | D12: {*d|var:specificationName|locked} | F12: LAST: | G12: {*d|var:scLast|locked|ft:com.lcs.wc.product.LCSProduct}
C15: COST SUMMARY
D17: COST INPUTS | G17: FOB BREAKDOWN | K17: LABOR & OVERHEAD
D19: Vendor Cost Sheet Status | G19: Total Materials | H19: =IF(H26>0,H26,(SUM(H20:H25))) -> 0 | K19: UPPER PREPARATION | M19: Flex Attribtue Name (hide on doc) | N19: TCT (mins) | O19: STOCKFITTING | Q19: Flex Attribtue Name (hide on doc) | R19: TCT (mins) | V19: Additional Override Attributes
D20: Incoterms | G20: Total Upper | H20: =SUMIF(C51:C201,'Data Validation'!A2,S51:S201)+SUMIF(C206:C220,'Data Validation'!A2,S206:S211) -> 0 | I20: BOM + Additional BOM | K20: # Textile/ synthetic pcs. | L20: =W49 -> 0 | M20: # Textile/ synthetic pcs. TCT (mins) | N20: =VLOOKUP(CONCATENATE("# Cut & Prep NON-LEATHER",L20),'TCT Lookup'!A:E,5,FALSE) -> 0 | O20: # Bottom pieces | P20: =AF49 -> 0 | Q20: # Bottom pieces TCT (mins) | R20: =IFERROR(VLOOKUP(CONCATENATE("# Bottom pieces",P20),'TCT Lookup'!A:E,5,FALSE),0) -> 0 | V20: =SUMIF(C206:C220,'Data Validation'!A2,S206:S211) -> 0
D21: Incoterms Location | G21: Total Sockliner | H21: =SUMIF(C51:C201,'Data Validation'!A3,S51:S201)+SUMIF(C206:C220,'Data Validation'!A3,S206:S211) -> 0 | I21: BOM + Additional BOM | K21: # Textile/ synthetic pcs for single layer cutting | L21: =X49 -> 0 | M21: # Textile/ synthetic pcs for single layer cutting TCT (mins) | N21: =VLOOKUP(CONCATENATE("# Cut & Prep Non-leather pieces for single layer cutting",L21),'TCT Lookup'!A:E,5,FALSE) -> 0 | O21: # Recess points and # Emboss/deboss windows | P21: 1 | Q21: # Recess points and # Emboss/deboss windows TCT (mins) | R21: =IFERROR(VLOOKUP(CONCATENATE("# Recess points and # Emboss/deboss windows",P21),'TCT Lookup'!A:E,5,FALSE),0) -> 0.2141914 | V21: =SUMIF(C206:C220,'Data Validation'!A3,S206:S211) -> 0
D22: Quote Good From | E22: {*du|var:scQuoteGoodFrom|ft:com.lcs.wc.sourcing.LCSCostSheet|param:DATE_FORMAT~mm/dd/yyyy} | G22: Total Insole | H22: =SUMIF(C51:C201,'Data Validation'!A4,S51:S201)+SUMIF(C206:C220,'Data Validation'!A4,S206:S211) -> 0 | I22: BOM + Additional BOM | K22: # Cut & Prep LEATHER | L22: =Y49 -> 0 | M22: # Cut & Prep LEATHER TCT (mins) | N22: =VLOOKUP(CONCATENATE("# Cut & Prep LEATHER",L22),'TCT Lookup'!A:E,5,FALSE) -> 0 | O22: ASSEMBLY | R22: TCT (mins) | V22: =SUMIF(C206:C220,'Data Validation'!A4,S206:S211) -> 0
D23: Quote Good Until | E23: {*du|var:scQuoteGoodUntil|ft:com.lcs.wc.sourcing.LCSCostSheet|param:DATE_FORMAT~mm/dd/yyyy} | G23: Total Bottom | H23: =SUMIF(C51:C201,'Data Validation'!A5,S51:S201)+SUMIF(C206:C220,'Data Validation'!A5,S206:S211) -> 0 | I23: BOM + Additional BOM | K23: Pair Matching | L23: =Z49 -> 0 | M23: # Pair Matching TCT (mins) | N23: =IFERROR(VLOOKUP(CONCATENATE("# Cut & Prep LEATHER PAIR MATCHING",L23),'TCT Lookup'!A:E,5,FALSE),0) -> 0 | O23: Heel counter 1 | Q23: Heel counter TCT (mins) | R23: =IFERROR(VLOOKUP(CONCATENATE("Heel counter",P23),'TCT Lookup'!A:E,5,FALSE),0) -> 0 | V23: =SUMIF(C206:C220,'Data Validation'!A5,S206:S211) -> 0
D24: Quote Units | E24: {*du|var:scQuoteUnits|ft:com.lcs.wc.sourcing.LCSCostSheet} | G24: Total Sundries | H24: =SUMIF(C51:C201,'Data Validation'!A6,S51:S201)+SUMIF(C206:C220,'Data Validation'!A6,S206:S211) -> 0 | I24: BOM + Additional BOM | K24: Shoes Height | M24: # Pair Matching TCT (mins) | N24: =IFERROR(VLOOKUP(CONCATENATE("Shoes Height",L24),'TCT Lookup'!A:E,5,FALSE),0) -> 0 | O24: Heel counter 2 | Q24: Heel counter TCT (mins) | R24: =IFERROR(VLOOKUP(CONCATENATE("Heel counter",P24),'TCT Lookup'!A:E,5,FALSE),0) -> 0 | V24: =SUMIF(C206:C220,'Data Validation'!A6,S206:S211) -> 0
D25: First Sale Markup | E25: {*du|var:scFirstSaleMarkup|ft:com.lcs.wc.sourcing.LCSCostSheet} | G25: Total Packaging | H25: =SUMIF(C51:C201,'Data Validation'!A7,S51:S201)+SUMIF(C206:C220,'Data Validation'!A7,S206:S211) -> 0 | I25: BOM + Additional BOM | K25: # of stitched upper pcs | L25: =AA49 -> 0 | M25: # of stitched upper pcs TCT (mins) | N25: =VLOOKUP(CONCATENATE("# Stitched upper pieces",L25),'TCT Lookup'!A:E,5,FALSE) -> 0 | O25: Construction type | Q25: Construction type TCT (mins) | R25: =IFERROR(VLOOKUP(CONCATENATE(O25,P25),'TCT Lookup'!A:E,5,FALSE),0) -> 0 | V25: =SUMIF(C206:C220,'Data Validation'!A7,S206:S211) -> 0
D26: Vendor Cost Comments | E26: {*du|var:scVendorCostComments|ft:com.lcs.wc.sourcing.LCSCostSheet} | G26: BOM Override | H26: 0 | K26: # Stitch and Turn | L26: =AB49 -> 0 | M26: # Stitch and Turn TCT (mins) | N26: =VLOOKUP(CONCATENATE("# Stitch & turns",L26),'TCT Lookup'!A:E,5,FALSE) -> 0 | O26: Outsole stitching | Q26: Outsole stitching TCT (mins) | R26: =IFERROR(VLOOKUP(CONCATENATE(O26,P26),'TCT Lookup'!A:E,5,FALSE),0) -> 0
G27: LOH Total | H27: =SUM(H28:H31) -> 43.945291 | K27: # Folded Edge | L27: =AC49 -> 0 | M27: # Folded Edge TCT (mins) | N27: =IFERROR(VLOOKUP(CONCATENATE("# Folded edges",L27),'TCT Lookup'!A:E,5,FALSE),0) -> 0 | O27: Upper & Bottom Line-Up | R27: =IFERROR(VLOOKUP(CONCATENATE(O27,P27),'TCT Lookup'!A:E,5,FALSE),0) -> 0
D28: LOH Rate | E28: =SUM(E29:E30) -> 8 | G28: Upper Preparation | H28: =SUM((N20:N27),(N30:N34),(N36:N38),(N40:N43))*E28 -> 42.23176 | I28: Sum of Upper Preparation * LOH Rate | K28: Special upper construction | M28: Special upper construction TCT (mins) | N28: =IFERROR(VLOOKUP(CONCATENATE("Special upper construction",L28),'TCT Lookup'!A:E,5,FALSE),0) -> 0 | O28: Sockliner | Q28: Sockliner TCT (mins) | R28: =IFERROR(VLOOKUP(CONCATENATE(O28,P28),'TCT Lookup'!A:E,5,FALSE),0) -> 0
D29: Labor Rate | E29: 5 | G29: Stockfitting | H29: =SUM(R20:R21)*E28 -> 1.7135312 | I29: Sum of Stockfitting * LOH Rate | K29: Lacing system | O29: # attached components during assembly | P29: =AG49 -> 0 | Q29: # Attached components during assembly TCT (mins) | R29: =IFERROR(VLOOKUP(CONCATENATE(O29,P29),'TCT Lookup'!A:E,5,FALSE),0) -> 0
D30: OH Rate | E30: 3 | G30: Assembly | H30: =IFERROR(SUM(R23:R31)*E28,0) -> 0 | I30: Sum of Assembly * LOH Rate | K30: Punch holes | L30: 1 | M30: Punch holes TCT (mins) | N30: =IFERROR(VLOOKUP(CONCATENATE("# Punch holes",L30),'TCT Lookup'!A:E,5,FALSE),0) -> 0.051502146 | O30: Lacing | Q30: Lacing TCT (mins) | R30: =IFERROR(VLOOKUP(CONCATENATE(O30,P30),'TCT Lookup'!A:E,5,FALSE),0) -> 0
G31: Other process | H31: =SUM(R33:R39)*E28 -> 0 | I31: Sum of Other process * LOH Rate | K31: Metal eyelets | L31: 4 | M31: Metal eyelets TCT (mins) | N31: =IFERROR(VLOOKUP(CONCATENATE("# Metal eyelets",L31),'TCT Lookup'!A:E,5,FALSE),0) -> 0.41201717 | O31: Packaging | Q31: Packaging TCT (mins) | R31: =IFERROR(VLOOKUP(CONCATENATE(O31,P31),'TCT Lookup'!A:E,5,FALSE),0) -> 0
D32: Profit % | E32: 5 | G32: Profit | H32: =(H19+H27)*(E32/100) -> 2.1972645 | I32: (LOH + Materials) * Tooling | K32: Inserted lace loops | L32: 1 | M32: Inserted lace loops TCT (mins) | N32: =IFERROR(VLOOKUP(CONCATENATE("# Lace loops (inserted)",L32),'TCT Lookup'!A:E,5,FALSE),0) -> 0.90128755 | O32: OTHER PROCESSES | R32: TCT (mins)
D33: Overhead Premium % | E33: 5 | G33: Tooling | H33: 0 | K33: Stitched on lace loops | L33: 1 | M33: Stitched on lace loops TCT (mins) | N33: =IFERROR(VLOOKUP(CONCATENATE("# Lace loops (stitched on)",L33),'TCT Lookup'!A:E,5,FALSE),0) -> 0.33476395 | P33: =IF(COUNTA(P34,P35,P36,P37,P38,P39)=0, "", IF(COUNTA(P34,P35,P36,P37,P38,P39)=1, IF(P34<>"", P34, IF(P35<>"", P35, IF(P36<>"", P36, IF(P37<>"", P37, IF(P38<>"", P38, P39))))), P34&IF(P35<>"", "; "&P35, "")&IF(P36<>"", "; "&P36, "")&IF(P37<>"", "; "&P37, "")&IF(P38<>"", "; "&P38, "")&IF(P39<>"", "; "&P39, ""))) | Q33: Other Processes TCT (mins) | R33: =SUM(R34:R39) -> 0
G34: Overhead Premium $ | H34: =IF(ISERROR((H19+H27+H32+H33)/(1/(E33/100)-1)),0,(H19+H27+H32+H33)/(1/(E33/100)-1)) -> 2.4285555 | K34: Ghillies | L34: 1 | M34: Ghillies TCT (mins) | N34: =IFERROR(VLOOKUP(CONCATENATE("# Ghillies",L34),'TCT Lookup'!A:E,5,FALSE),0) -> 0.36051502 | R34: 0
G35: Vendor Cost | H35: =H19+H27+H32+H33+H34 -> 48.571111 | K35: Types and # of special stitch
K36: Lock stitch/overlock stitch/Flat Stitch | L36: 1 | M36: Lock stitch/Overlock Stitch/Flat Stitch TCT (mins) | N36: =IFERROR(VLOOKUP(CONCATENATE("# Lock stitch/overlock stitch/Flat stitch",L36),'TCT Lookup'!A:E,5,FALSE),0) -> 0.38626609
K37: Box stitch | L37: 1 | M37: Box Stitch TCT (mins) | N37: =IFERROR(VLOOKUP(CONCATENATE("# Box stitch",L37),'TCT Lookup'!A:E,5,FALSE),0) -> 0.36051502 | R37: 0
K38: Triple stitch | L38: 1 | M38: Triple stitch TCT (mins) | N38: =IFERROR(VLOOKUP(CONCATENATE("# Triple stitch",L38),'TCT Lookup'!A:E,5,FALSE),0) -> 0.54077253 | R38: 0
K39: Types and # of binding | R39: 0
K40: English binding | L40: =AD49 -> 0 | M40: English binding TCT (mins) | N40: =IFERROR(VLOOKUP(CONCATENATE("# English (incl. piping)",L40),'TCT Lookup'!A:E,5,FALSE),0) -> 0
K41: French binding | L41: =AE49 -> 0 | M41: French binding TCT (mins) | N41: =IFERROR(VLOOKUP(CONCATENATE("# French binding",L41),'TCT Lookup'!A:E,5,FALSE),0) -> 0
K42: No sew binding | L42: 3 | M42: No sew binding TCT (mins) | N42: =IFERROR(VLOOKUP(CONCATENATE("# No sew binding",L42),'TCT Lookup'!A:E,5,FALSE),0) -> 1.9313305 | P42: Total Cycle Time | R42: =SUM(R33:R39,R23:R31,R20:R21,N20:N28,N30:N34,N40:N43,N36:N38) -> 5.4931614
K43: Pocket construction | M43: Pocket construction TCT (mins) | N43: =IFERROR(VLOOKUP(CONCATENATE("Pocket construction", L43),'TCT Lookup'!A:E,5,FALSE),0) -> 0
C48: BILL OF MATERIALS | W48: UPPER PREPARATION | AF48: Stockfitting | AG48: Assembly
W49: =SUM(W51:W213) -> 0 | X49: =SUM(X51:X213) -> 0 | Y49: =SUM(Y51:Y213) -> 0 | Z49: =SUM(Z51:Z213) -> 0 | AA49: =SUM(AA51:AA213) -> 0 | AB49: =SUM(AB51:AB213) -> 0 | AC49: =SUM(AC51:AC213) -> 0 | AD49: =SUM(AD51:AD213) -> 0 | ... AG49: =SUM(AG51:AG213) -> 0
C50: Section | D50: Component or Location | E50: Material ID | F50: Material Name | G50: Supplier | H50: Comment | I50: BOM UOM | J50: BOM Price | K50: Price OVR | L50: CIF | N50: Quantity | O50: Wastage % | P50: Calculation Size % | R50: Gross Quantity | S50: Total Mat Cost | T50: BOM Link ID | W50: # Textile/ synthetic pcs. | X50: # Textile/ synthetic pcs for single layer cutting | Y50: # Cut & Prep LEATHER | Z50: Pair Matching | AA50: # of stitched upper pcs | AB50: # Stitch and Turn | AC50: # Folded Edge | AD50: English binding | AE50: French binding | AF50: No. of total bottom pieces | AG50: No. of attached components during assembly
D51: {*d|var:scComponent|dir:column|grouped|locked|ft:com.lcs.wc.flexbom.FlexBOMLink|param:HRR~true|param:RR~150} | E51: {*d|var:scMaterialNo|dir:column|grouped|locked|ft:com.lcs.wc.material.LCSMaterial|param:HRR~true|param:RR~150} | F51: {*d|var:materialDescription|dir:column|grouped|locked|ft:com.lcs.wc.flexbom.FlexBOMLink|param:HRR~true|param:RR~150} | G51: {*d|var:name|dir:column|grouped|locked|ft:com.lcs.wc.supplier.LCSSupplier|param:HRR~true|param:RR~150} | H51: {*d|var:scComments|dir:column|grouped|locked|ft:com.lcs.wc.flexbom.FlexBOMLink|param:HRR~true|param:RR~150} | I51: {*d|var:bomUOM|dir:column|grouped|locked|param:HRR~true|param:RR~150} | J51: {*d|var:materialPrice|dir:column|grouped|locked|ft:com.lcs.wc.material.LCSMaterialSupplier|param:HRR~true|param:RR~150} | K51: {*du|var:priceOverride|dir:column|grouped|ft:com.lcs.wc.flexbom.FlexBOMLink|param:HRR~true|param:RR~150} | L51: {*du|var:scCIF|dir:column|grouped|ft:com.lcs.wc.flexbom.FlexBOMLink|param:HRR~true|param:RR~150} | N51: {*du|var:quantity|dir:column|grouped|ft:com.lcs.wc.flexbom.FlexBOMLink|param:HRR~true|param:RR~150} | O51: {*du|var:lossAdjustment|dir:column|grouped|ft:com.lcs.wc.flexbom.FlexBOMLink|param:HRR~true|param:RR~150} | P51: {*du|var:scCalculationSizePercent|dir:column|grouped|ft:com.lcs.wc.flexbom.FlexBOMLink|param:HRR~true|param:RR~150} | R51: =N51*(1+O51)*(1+P51) -> #VALUE! | S51: =IF(OR(K51<>0,K51<>""),(K51+L51)*R51,R51*(J51+L51)) -> #VALUE! | T51: {*du|var:bomLinkId|dir:column|grouped|locked|param:HRR~true|param:RR~150}
R52: =N52*(1+O52)*(1+P52) -> 0 | S52: =IF(OR(K52<>0,K52<>""),(K52+L52)*R52,R52*(J52+L52)) -> 0
R53: =N53*(1+O53)*(1+P53) -> 0 | S53: =IF(OR(K53<>0,K53<>""),(K53+L53)*R53,R53*(J53+L53)) -> 0
R54: =N54*(1+O54)*(1+P54) -> 0 | S54: =IF(OR(K54<>0,K54<>""),(K54+L54)*R54,R54*(J54+L54)) -> 0
R55: =N55*(1+O55)*(1+P55) -> 0 | S55: =IF(OR(K55<>0,K55<>""),(K55+L55)*R55,R55*(J55+L55)) -> 0
R56: =N56*(1+O56)*(1+P56) -> 0 | S56: =IF(OR(K56<>0,K56<>""),(K56+L56)*R56,R56*(J56+L56)) -> 0
R57: =N57*(1+O57)*(1+P57) -> 0 | S57: =IF(OR(K57<>0,K57<>""),(K57+L57)*R57,R57*(J57+L57)) -> 0
R58: =N58*(1+O58)*(1+P58) -> 0 | S58: =IF(OR(K58<>0,K58<>""),(K58+L58)*R58,R58*(J58+L58)) -> 0
R59: =N59*(1+O59)*(1+P59) -> 0 | S59: =IF(OR(K59<>0,K59<>""),(K59+L59)*R59,R59*(J59+L59)) -> 0
R60: =N60*(1+O60)*(1+P60) -> 0 | S60: =IF(OR(K60<>0,K60<>""),(K60+L60)*R60,R60*(J60+L60)) -> 0
R61: =N61*(1+O61)*(1+P61) -> 0 | S61: =IF(OR(K61<>0,K61<>""),(K61+L61)*R61,R61*(J61+L61)) -> 0
R62: =N62*(1+O62)*(1+P62) -> 0 | S62: =IF(OR(K62<>0,K62<>""),(K62+L62)*R62,R62*(J62+L62)) -> 0
R63: =N63*(1+O63)*(1+P63) -> 0 | S63: =IF(OR(K63<>0,K63<>""),(K63+L63)*R63,R63*(J63+L63)) -> 0
... R201: =N201*(1+O201)*(1+P201) -> 0 | S201: =IF(OR(K201<>0,K201<>""),(K201+L201)*R201,R201*(J201+L201)) -> 0
C203: ADDITIONAL BOM ITEMS | W203: UPPER PREPARATION | AF203: Stockfitting | AG203: Assembly
C205: Section | D205: Component or Location | E205: Material ID | F205: Material Name | G205: Supplier | H205: Comment | I205: BOM UOM | J205: BOM Price | K205: Price OVR | L205: CIF | N205: Quantity | O205: Wastage % | P205: Calculation Size % | R205: Gross Quantity | S205: Total Mat Cost | T205: Additional | W205: # Textile/ synthetic pcs. | X205: # Textile/ synthetic pcs for single layer cutting | Y205: # Cut & Prep LEATHER | Z205: Pair Matching | AA205: # of stitched upper pcs | AB205: # Stitch and Turn | AC205: # Folded Edge | AD205: English binding | AE205: French binding | AF205: No. of total bottom pieces | AG205: No. of attached components during assembly
R206: =N206*(1+O206)*(1+P206) -> 0 | S206: =IF(OR(K206<>0,K206<>""),(K206+L206)*R206,R206*(J206+L206)) -> 0 | T206: =IF(C206<>"",TRUE,"")
R207: =N207*(1+O207)*(1+P207) -> 0 | S207: =IF(OR(K207<>0,K207<>""),(K207+L207)*R207,R207*(J207+L207)) -> 0 | T207: =IF(C207<>"",TRUE,"")
R208: =N208*(1+O208)*(1+P208) -> 0 | S208: =IF(OR(K208<>0,K208<>""),(K208+L208)*R208,R208*(J208+L208)) -> 0 | T208: =IF(C208<>"",TRUE,"")
R209: =N209*(1+O209)*(1+P209) -> 0 | S209: =IF(OR(K209<>0,K209<>""),(K209+L209)*R209,R209*(J209+L209)) -> 0 | T209: =IF(C209<>"",TRUE,"")
R210: =N210*(1+O210)*(1+P210) -> 0 | S210: =IF(OR(K210<>0,K210<>""),(K210+L210)*R210,R210*(J210+L210)) -> 0 | T210: =IF(C210<>"",TRUE,"")
R211: =N211*(1+O211)*(1+P211) -> 0 | S211: =IF(OR(K211<>0,K211<>""),(K211+L211)*R211,R211*(J211+L211)) -> 0 | T211: =IF(C211<>"",TRUE,"")
R212: =N212*(1+O212)*(1+P212) -> 0 | S212: =IF(OR(K212<>0,K212<>""),(K212+L212)*R212,R212*(J212+L212)) -> 0 | T212: =IF(C212<>"",TRUE,"")
R213: =N213*(1+O213)*(1+P213) -> 0 | S213: =IF(OR(K213<>0,K213<>""),(K213+L213)*R213,R213*(J213+L213)) -> 0 | T213: =IF(C213<>"",TRUE,"")
R214: =N214*(1+O214)*(1+P214) -> 0 | S214: =IF(OR(K214<>0,K214<>""),(K214+L214)*R214,R214*(J214+L214)) -> 0 | T214: =IF(C214<>"",TRUE,"")
R215: =N215*(1+O215)*(1+P215) -> 0 | S215: =IF(OR(K215<>0,K215<>""),(K215+L215)*R215,R215*(J215+L215)) -> 0 | T215: =IF(C215<>"",TRUE,"")
R216: =N216*(1+O216)*(1+P216) -> 0 | S216: =IF(OR(K216<>0,K216<>""),(K216+L216)*R216,R216*(J216+L216)) -> 0 | T216: =IF(C216<>"",TRUE,"")
R217: =N217*(1+O217)*(1+P217) -> 0 | S217: =IF(OR(K217<>0,K217<>""),(K217+L217)*R217,R217*(J217+L217)) -> 0 | T217: =IF(C217<>"",TRUE,"")
... R220: =N220*(1+O220)*(1+P220) -> 0 | S220: =IF(OR(K220<>0,K220<>""),(K220+L220)*R220,R220*(J220+L220)) -> 0 | T220: =IF(C220<>"",TRUE,"")

Sheet Data Validation
A1: Section | B1: Special upper construction | C1: Pocket construction | D1: Heel counter | E1: Construction type | F1: Outsole stitching | G1: Sockliner | H1: Lacing | I1: Packaging | J1: Cost Sheet Milestone | K1: Incoterms | L1: Vendor Cost Sheet Status | M1: Destination | N1: Sample Size | O1: Shoes Height | P1: Upper & Bottom Line-Up | Q1: Incoterms Location
A2: Upper | B2: None | C2: Yes | D2: No heel counter | E2: Board | F2: None | G2: Cemented sockliner | H2: No lacing | I2: Normal packaging | J2: {*d|var:scMilestoneStatus|ft:com.lcs.wc.sourcing.LCSCostSheet|dir:column|param:ENUM_EXPORT~Y} | K2: {*d|var:scIncoterms|ft:com.lcs.wc.sourcing.LCSCostSheet|dir:column|param:ENUM_EXPORT~Y} | L2: Draft | N2: W7 | O2: KIDS Low/mid cut | P2: Yes | Q2: {*d|var:scIncotermlocation|ft:com.lcs.wc.sourcing.LCSCostSheet|dir:column|param:OBJ_REF_LIST_EXPORT~Y}
A3: Sockliner | B3: Lining/Half bootie construction | C3: No | D3: TR heel counter | E3: Board Vulcanized | F3: 1 x half stitching | G3: Drop-in sockliner | H3: Normal threading | I3: Special packaging | L3: Requested | N3: M9 | O3: KIDS High cut | P3: No
A4: Insole | B4: Tongue wing construction | D4: Thermo sheet heel counter | E4: Cold cement foxing | F4: 2 x half stitching | G4: No sockliner | H4: Additional spare laces | L4: Vendor Submitted | N4: M11 | O4: KIDS Boot cut
A5: Bottom | B5: Gusset/Bootie construction | D5: External heel counter (glued) | E5: Full Feather/Cage | F5: Full stitching | H5: Special lacing for cosmetic effects | L5: In Negotiation | N5: U9 | O5: ADULT Low/mid cut
A6: Sundries | E6: Half Feather | L6: Negotiated | N6: Special Sample | O6: ADULT High cut
A7: Packaging | E7: Moccasin | L7: Rejected | O7: ADULT Boot cut
E8: Strobel
E9: Strobel & half board
E10: Strobel & board
E11: Strobel & Toe Lasting
E12: Strobel forefoot & heel stitching
E13: Strobel to midsole
E14: Strobel Vulcanized
E15: Top plate/Bottom plate construction
E16: Triple lasting
E17: Upper stitching to outsole

Sheet TCT Lookup
A1: Id | B1: Complexity Group | C1: Complexity Criteria | D1: Criteria Details/ Quantity | E1: Cycle Time in Mins
A2: # Attached components during assembly0 | B2: Assembly | C2: # Attached components during assembly | D2: 0 | E2: 0
A3: # Attached components during assembly1 | B3: Assembly | C3: # Attached components during assembly | D3: 1 | E3: 2.5236052
A4: # Attached components during assembly2 | B4: Assembly | C4: # Attached components during assembly | D4: 2 | E4: 5.0729614
A5: # Attached components during assembly3 | B5: Assembly | C5: # Attached components during assembly | D5: 3 | E5: 7.5965665
A6: # Attached components during assembly4 | B6: Assembly | C6: # Attached components during assembly | D6: 4 | E6: 10.120172
A7: # Attached components during assembly5 | B7: Assembly | C7: # Attached components during assembly | D7: 5 | E7: 12.669528
A8: # Attached components during assembly6 | B8: Assembly | C8: # Attached components during assembly | D8: 6 | E8: 15.201717
A9: # Attached components during assembly7 | B9: Assembly | C9: # Attached components during assembly | D9: 7 | E9: 17.716738
A10: # Attached components during assembly8 | B10: Assembly | C10: # Attached components during assembly | D10: 8 | E10: 20.274678
A11: # Attached components during assembly9 | B11: Assembly | C11: # Attached components during assembly | D11: 9 | E11: 22.7897
A12: # Attached components during assembly10 | B12: Assembly | C12: # Attached components during assembly | D12: 10 | E12: 25.313305
A13: # English (incl. piping)0 | B13: Binding | C13: # English (incl. piping) | D13: 0 | E13: 0
A14: # English (incl. piping)1 | B14: Binding | C14: # English (incl. piping) | D14: 1 | E14: 0.38626609
A15: # English (incl. piping)2 | B15: Binding | C15: # English (incl. piping) | D15: 2 | E15: 0.77253219
A16: # English (incl. piping)3 | B16: Binding | C16: # English (incl. piping) | D16: 3 | E16: 1.1587983
A17: # English (incl. piping)4 | B17: Binding | C17: # English (incl. piping) | D17: 4 | E17: 1.5450644
A18: # English (incl. piping)5 | B18: Binding | C18: # English (incl. piping) | D18: 5 | E18: 1.9313305
A19: # English (incl. piping)6 | B19: Binding | C19: # English (incl. piping) | D19: 6 | E19: 2.3175966
A20: # English (incl. piping)7 | B20: Binding | C20: # English (incl. piping) | D20: 7 | E20: 2.7038627
A21: # English (incl. piping)8 | B21: Binding | C21: # English (incl. piping) | D21: 8 | E21: 3.0901288
A22: # English (incl. piping)9 | B22: Binding | C22: # English (incl. piping) | D22: 9 | E22: 3.4763948
A23: # English (incl. piping)10 | B23: Binding | C23: # English (incl. piping) | D23: 10 | E23: 3.8626609
A24: # English (incl. piping)11 | B24: Binding | C24: # English (incl. piping) | D24: 11 | E24: 4.248927
A25: # English (incl. piping)12 | B25: Binding | C25: # English (incl. piping) | D25: 12 | E25: 4.6351931
... A336: # Recess points and # Emboss/deboss windows99 | B336: Bottom | C336: # Recess points and # Emboss/deboss windows | D336: 99 | E336: 1.4230569
A337: Construction typeBoard | B337: Construction type | C337: Construction type | D337: Board | E337: 9.2703863
A338: Construction typeBoard Vulcanized | B338: Construction type | C338: Construction type | D338: Board Vulcanized | E338: 14.420601
A339: Construction typeCold cement foxing | B339: Construction type | C339: Construction type | D339: Cold cement foxing | E339: 11.072961
A340: Construction typeFull Feather/Cage | B340: Construction type | C340: Construction type | D340: Full Feather/Cage | E340: 16.738197
A341: Construction typeHalf Feather | B341: Construction type | C341: Construction type | D341: Half Feather | E341: 14.16309
A342: Construction typeMoccasin | B342: Construction type | C342: Construction type | D342: Moccasin | E342: 9.527897
A343: Construction typeStrobel | B343: Construction type | C343: Construction type | D343: Strobel | E343: 9.0128755
A344: Construction typeStrobel & half board | B344: Construction type | C344: Construction type | D344: Strobel & half board | E344: 11.330472
A345: Construction typeStrobel & board | B345: Construction type | C345: Construction type | D345: Strobel & board | E345: 11.845494
A346: Construction typeStrobel & Toe Lasting | B346: Construction type | C346: Construction type | D346: Strobel & Toe Lasting | E346: 10.55794
A347: Construction typeStrobel forefoot & heel stitching | B347: Construction type | C347: Construction type | D347: Strobel forefoot & heel stitching | E347: 9.7854077
A348: Construction typeStrobel to midsole | B348: Construction type | C348: Construction type | D348: Strobel to midsole | E348: 9.527897
... A352: Construction typeUpper stitching to outsole | B352: Construction type | C352: Construction type | D352: Upper stitching to outsole | E352: 5.9227468
A353: # Cut & Prep LEATHER0 | B353: Cut & Prep | C353: # Cut & Prep LEATHER | D353: 0 | E353: 0
A354: # Cut & Prep LEATHER1 | B354: Cut & Prep | C354: # Cut & Prep LEATHER | D354: 1 | E354: 0.35021459
A355: # Cut & Prep LEATHER2 | B355: Cut & Prep | C355: # Cut & Prep LEATHER | D355: 2 | E355: 0.70042918
A356: # Cut & Prep LEATHER3 | B356: Cut & Prep | C356: # Cut & Prep LEATHER | D356: 3 | E356: 1.0506438
A357: # Cut & Prep LEATHER4 | B357: Cut & Prep | C357: # Cut & Prep LEATHER | D357: 4 | E357: 1.4008584
A358: # Cut & Prep LEATHER5 | B358: Cut & Prep | C358: # Cut & Prep LEATHER | D358: 5 | E358: 1.751073
A359: # Cut & Prep LEATHER6 | B359: Cut & Prep | C359: # Cut & Prep LEATHER | D359: 6 | E359: 2.1012876
A360: # Cut & Prep LEATHER7 | B360: Cut & Prep | C360: # Cut & Prep LEATHER | D360: 7 | E360: 2.4515021
A361: # Cut & Prep LEATHER8 | B361: Cut & Prep | C361: # Cut & Prep LEATHER | D361: 8 | E361: 2.8017167
A362: # Cut & Prep LEATHER9 | B362: Cut & Prep | C362: # Cut & Prep LEATHER | D362: 9 | E362: 3.1519313
A363: # Cut & Prep LEATHER10 | B363: Cut & Prep | C363: # Cut & Prep LEATHER | D363: 10 | E363: 3.5021459
A364: # Cut & Prep LEATHER11 | B364: Cut & Prep | C364: # Cut & Prep LEATHER | D364: 11 | E364: 3.8523605
... A525: # Cut & Prep Non-leather pieces for single layer cutting20 | B525: Cut & Prep | C525: # Cut & Prep Non-leather pieces for single layer cutting | D525: 20 | E525: 8.2403433
A526: Heel counterExternal heel counter (glued) | B526: Heel counter | C526: Heel counter | D526: =A526*(1+B526)*(1+C526) -> #VALUE! | E526: 3.6051502
A527: Heel counterNo heel counter | B527: Heel counter | C527: Heel counter | D527: No heel counter | E527: 0
A528: Heel counterThermo sheet heel counter | B528: Heel counter | C528: Heel counter | D528: Thermo sheet heel counter | E528: 1.2875536
A529: Heel counterTR heel counter | B529: Heel counter | C529: Heel counter | D529: TR heel counter | E529: 0.72103004
A530: LacingAdditional spare laces | B530: Lacing | C530: Lacing | D530: Additional spare laces | E530: 1.5450644
A531: LacingNo lacing | B531: Lacing | C531: Lacing | D531: No lacing | E531: 0
A532: LacingNormal threading | B532: Lacing | C532: Lacing | D532: Normal threading | E532: 1.1587983
A533: LacingSpecial lacing for cosmetic effects | B533: Lacing | C533: Lacing | D533: Special lacing for cosmetic effects | E533: 1.6738197
A534: # Ghillies0 | B534: Lacing system & quantity | C534: # Ghillies | D534: 0 | E534: 0
A535: # Ghillies1 | B535: Lacing system & quantity | C535: # Ghillies | D535: 1 | E535: 0.36051502
A536: # Ghillies2 | B536: Lacing system & quantity | C536: # Ghillies | D536: 2 | E536: 0.72103004
A537: # Ghillies3 | B537: Lacing system & quantity | C537: # Ghillies | D537: 3 | E537: 1.0815451
A538: # Ghillies4 | B538: Lacing system & quantity | C538: # Ghillies | D538: 4 | E538: 1.4420601
A539: # Ghillies5 | B539: Lacing system & quantity | C539: # Ghillies | D539: 5 | E539: 1.8025751
A540: # Ghillies6 | B540: Lacing system & quantity | C540: # Ghillies | D540: 6 | E540: 2.1630901
A541: # Ghillies7 | B541: Lacing system & quantity | C541: # Ghillies | D541: 7 | E541: 2.5236052
A542: # Ghillies8 | B542: Lacing system & quantity | C542: # Ghillies | D542: 8 | E542: 2.8841202
A543: # Ghillies9 | B543: Lacing system & quantity | C543: # Ghillies | D543: 9 | E543: 3.2446352
A544: # Ghillies10 | B544: Lacing system & quantity | C544: # Ghillies | D544: 10 | E544: 3.6051502
A545: # Ghillies11 | B545: Lacing system & quantity | C545: # Ghillies | D545: 11 | E545: 3.9656652
... A738: # Punch holes40 | B738: Lacing system & quantity | C738: # Punch holes | D738: 40 | E738: 2.0600858
A739: Lacing systemNo holes | B739: Lacing system & quantity | C739: Lacing system | D739: No holes | E739: 0
A740: # Box stitch0 | B740: No. of special stitches | C740: # Box stitch | D740: 0 | E740: 0
A741: # Box stitch1 | B741: No. of special stitches | C741: # Box stitch | D741: 1 | E741: 0.36051502
A742: # Box stitch2 | B742: No. of special stitches | C742: # Box stitch | D742: 2 | E742: 0.72103004
A743: # Box stitch3 | B743: No. of special stitches | C743: # Box stitch | D743: 3 | E743: 1.0815451
A744: # Box stitch4 | B744: No. of special stitches | C744: # Box stitch | D744: 4 | E744: 1.4420601
A745: # Box stitch5 | B745: No. of special stitches | C745: # Box stitch | D745: 5 | E745: 1.8025751
A746: # Box stitch6 | B746: No. of special stitches | C746: # Box stitch | D746: 6 | E746: 2.1630901
A747: # Box stitch7 | B747: No. of special stitches | C747: # Box stitch | D747: 7 | E747: 2.5236052
A748: # Box stitch8 | B748: No. of special stitches | C748: # Box stitch | D748: 8 | E748: 2.8841202
A749: # Box stitch9 | B749: No. of special stitches | C749: # Box stitch | D749: 9 | E749: 3.2446352
A750: # Box stitch10 | B750: No. of special stitches | C750: # Box stitch | D750: 10 | E750: 3.6051502
A751: # Box stitch11 | B751: No. of special stitches | C751: # Box stitch | D751: 11 | E751: 3.9656652
... A983: # Triple stitch60 | B983: No. of special stitches | C983: # Triple stitch | D983: 60 | E983: 32.446352
A984: Outsole stitchingNone | B984: Outsole stitching | C984: Outsole stitching | D984: None | E984: 0
A985: Outsole stitching1 x half stitching | B985: Outsole stitching | C985: Outsole stitching | D985: 1 x half stitching | E985: 0.51502146
A986: Outsole stitching2 x half stitching | B986: Outsole stitching | C986: Outsole stitching | D986: 2 x half stitching | E986: 0.77253219
A987: Outsole stitchingFull stitching | B987: Outsole stitching | C987: Outsole stitching | D987: Full stitching | E987: 1.0300429
A988: PackagingNormal packaging | B988: Packaging | C988: Packaging | D988: Normal packaging | E988: 0.9527897
A989: PackagingSpecial packaging | B989: Packaging | C989: Packaging | D989: Special packaging | E989: 1.4678112
A990: SocklinerCemented sockliner | B990: Sockliner | C990: Sockliner | D990: Cemented sockliner | E990: 0.48927039
A991: SocklinerDrop-in sockliner | B991: Sockliner | C991: Sockliner | D991: Drop-in sockliner | E991: 0.23175966
A992: SocklinerNo sockliner | B992: Sockliner | C992: Sockliner | D992: No sockliner | E992: 0
A993: Special upper constructionNone | B993: Special upper construction | C993: Special upper construction | D993: None | E993: 0
A994: Special upper constructionGusset/Bootie construction | B994: Special upper construction | C994: Special upper construction | D994: Gusset/Bootie construction | E994: 1.2875536
A995: Special upper constructionLining/Half bootie construction | B995: Special upper construction | C995: Special upper construction | D995: Lining/Half bootie construction | E995: 0.77253219
A996: Special upper constructionTongue wing construction | B996: Special upper construction | C996: Special upper construction | D996: Tongue wing construction | E996: 0.38626609
...
